{"todos":[{"consecutivo":1,"fecha_de_corte":"2024-03-24","numero_cum":"123456","nombre_del_medicamento":"Paracetamol","forma_farmaceutica":"Tableta","descripcion_medicamento":"Analgesico y antipirético comúnmente utilizado para aliviar el dolor y reducir la fiebre.","valor_minimo":5,"valor_maximo":15},{"consecutivo":2,"fecha_de_corte":"2024-04-10","numero_cum":"789012","nombre_del_medicamento":"Omeprazol","forma_farmaceutica":"Cápsula","descripcion_medicamento":"Inhibidor de la bomba de protones utilizado para tratar el reflujo ácido y úlceras estomacales.","valor_minimo":10,"valor_maximo":20},{"consecutivo":3,"fecha_de_corte":"2024-03-24","numero_cum":"345678","nombre_del_medicamento":"Ibuprofeno","forma_farmaceutica":"Tableta","descripcion_medicamento":"Antiinflamatorio no esteroideo utilizado para aliviar el dolor, la inflamación y la fiebre.","valor_minimo":7,"valor_maximo":17},{"consecutivo":4,"fecha_de_corte":"2024-03-24","numero_cum":"901234","nombre_del_medicamento":"Amoxicilina","forma_farmaceutica":"Cápsula","descripcion_medicamento":"Antibiótico de amplio espectro utilizado para tratar infecciones bacterianas.","valor_minimo":8,"valor_maximo":25},{"consecutivo":5,"fecha_de_corte":"2024-03-24","numero_cum":"567890","nombre_del_medicamento":"Loratadina","forma_farmaceutica":"Tableta","descripcion_medicamento":"Antihistamínico utilizado para aliviar los síntomas de la alergia como la picazón, los estornudos y la secreción nasal.","valor_minimo":4,"valor_maximo":12},{"consecutivo":6}]}